django_simple_editorjs/__init__.py
django_simple_editorjs/apps.py
django_simple_editorjs/main.py
django_simple_editorjs/static/django-simple-editorjs/main.css
django_simple_editorjs/static/django-simple-editorjs/main.js
django_simple_editorjs/static/django-simple-editorjs/tools/checklist.js
django_simple_editorjs/static/django-simple-editorjs/tools/code.js
django_simple_editorjs/static/django-simple-editorjs/tools/delimiter.js
django_simple_editorjs/static/django-simple-editorjs/tools/embed.js
django_simple_editorjs/static/django-simple-editorjs/tools/header.js
django_simple_editorjs/static/django-simple-editorjs/tools/inline-code.js
django_simple_editorjs/static/django-simple-editorjs/tools/link.js
django_simple_editorjs/static/django-simple-editorjs/tools/list.js
django_simple_editorjs/static/django-simple-editorjs/tools/main.js
django_simple_editorjs/static/django-simple-editorjs/tools/marker.js
django_simple_editorjs/static/django-simple-editorjs/tools/quote.js
django_simple_editorjs/static/django-simple-editorjs/tools/simple-image.js
django_simple_editorjs/static/django-simple-editorjs/tools/table.js
django_simple_editorjs/static/django-simple-editorjs/tools/warning.js
django_simple_editorjs/templates/django-simple-editorjs/main.html
django_simple_editorjs-0.1.2.dist-info/LICENSE.txt
django_simple_editorjs-0.1.2.dist-info/METADATA
django_simple_editorjs-0.1.2.dist-info/WHEEL
django_simple_editorjs-0.1.2.dist-info/top_level.txt
django_simple_editorjs-0.1.2.dist-info/RECORD
