Metadata-Version: 2.1
Name: django-simple-editorjs
Version: 0.1.2
Summary: A simple editorjs for django
Home-page: https://github.com/gerardoaballesterjr/django-simple-editorjs
Author: Gerardo A. Ballester Jr.
Author-email: gerardoaballesterjr@gmail.com
License: MIT
Keywords: django simple editorjs
Classifier: Programming Language :: Python :: 3
Classifier: License :: OSI Approved :: MIT License
Classifier: Operating System :: OS Independent
Classifier: Framework :: Django
Requires-Python: >=3.4,<4.0
License-File: LICENSE.txt
